pycarsimlib/__init__.py
pycarsimlib/__main__.py
pycarsimlib/cli.py
pycarsimlib/core.py
pycarsimlib/logger.py
pycarsimlib/api/__init__.py
pycarsimlib/api/vs_solver.py
pycarsimlib/models/__init__.py
pycarsimlib/models/in_wheel_motored_vehicle.py
pycarsimlib/models/normal_vehicle.py
pycarsimlib/utils/__init__.py
pycarsimlib-0.0.1.dist-info/LICENSE.txt
pycarsimlib-0.0.1.dist-info/METADATA
pycarsimlib-0.0.1.dist-info/WHEEL
pycarsimlib-0.0.1.dist-info/entry_points.txt
pycarsimlib-0.0.1.dist-info/top_level.txt
pycarsimlib-0.0.1.dist-info/RECORD
